dju_intranet-0.3.2.dist-info/DESCRIPTION.rst
dju_intranet-0.3.2.dist-info/METADATA
dju_intranet-0.3.2.dist-info/RECORD
dju_intranet-0.3.2.dist-info/WHEEL
dju_intranet-0.3.2.dist-info/metadata.json
dju_intranet-0.3.2.dist-info/top_level.txt
djuintra/__init__.py
djuintra/util.py
