Metadata-Version: 2.0
Name: dju-intranet
Version: 0.3.2
Summary: Daejeon university intranet API
Home-page: https://github.com/Kjwon15/dju-intranet
Author: Kjwon15
Author-email: kjwonmail@gmail.com
License: UNKNOWN
Platform: UNKNOWN
Requires-Dist: fake-useragent (>=0.1.2)
Requires-Dist: lxml (>=3.4.0)
Requires-Dist: requests (>=2.4.3)
